[
  {
    "success": false,
    "error": "No keypoints detected",
    "num_keypoints_A": 0,
    "num_keypoints_B": 1,
    "image_name": "20241221_100711_257_IR_inferno",
    "pair_name": "pair_0001"
  },
  {
    "success": false,
    "error": "Insufficient matches",
    "num_keypoints_A": 1,
    "num_keypoints_B": 3,
    "num_matches": 0,
    "matching_stats": {
      "error": "Insufficient descriptors",
      "good_matches": 0
    },
    "image_name": "20241221_100711_257_IR_inferno",
    "pair_name": "pair_0002"
  },
  {
    "success": false,
    "error": "Insufficient matches",
    "num_keypoints_A": 4,
    "num_keypoints_B": 1,
    "num_matches": 0,
    "matching_stats": {
      "error": "Insufficient descriptors",
      "good_matches": 0
    },
    "image_name": "20241221_100711_257_IR_inferno",
    "pair_name": "pair_0003"
  },
  {
    "success": false,
    "error": "No keypoints detected",
    "num_keypoints_A": 0,
    "num_keypoints_B": 0,
    "image_name": "20241221_100711_257_IR_inferno",
    "pair_name": "pair_0004"
  },
  {
    "success": false,
    "error": "Insufficient matches",
    "num_keypoints_A": 3,
    "num_keypoints_B": 2,
    "num_matches": 2,
    "matching_stats": {
      "total_matches": 3,
      "good_matches": 2,
      "ratio_test_passed": 2,
      "ratio_test_failed": 1,
      "matching_time": 0.0,
      "ratio_threshold": 0.75,
      "mean_distance_ratio": 0.25210084033613445,
      "median_distance_ratio": 0.0
    },
    "image_name": "20241221_100711_257_IR_inferno",
    "pair_name": "pair_0005"
  },
  {
    "success": false,
    "error": "Insufficient matches",
    "num_keypoints_A": 7,
    "num_keypoints_B": 1,
    "num_matches": 0,
    "matching_stats": {
      "error": "Insufficient descriptors",
      "good_matches": 0
    },
    "image_name": "20241221_100711_257_IR_inferno",
    "pair_name": "pair_0006"
  },
  {
    "success": false,
    "error": "Insufficient matches",
    "num_keypoints_A": 2,
    "num_keypoints_B": 5,
    "num_matches": 1,
    "matching_stats": {
      "total_matches": 2,
      "good_matches": 1,
      "ratio_test_passed": 1,
      "ratio_test_failed": 1,
      "matching_time": 0.002006053924560547,
      "ratio_threshold": 0.75,
      "mean_distance_ratio": 0.4028776978417266,
      "median_distance_ratio": 0.4028776978417266
    },
    "image_name": "20241221_100711_257_IR_inferno",
    "pair_name": "pair_0007"
  },
  {
    "success": false,
    "error": "No keypoints detected",
    "num_keypoints_A": 0,
    "num_keypoints_B": 1,
    "image_name": "20241221_100711_257_IR_inferno",
    "pair_name": "pair_0008"
  },
  {
    "success": false,
    "error": "Insufficient matches",
    "num_keypoints_A": 3,
    "num_keypoints_B": 1,
    "num_matches": 0,
    "matching_stats": {
      "error": "Insufficient descriptors",
      "good_matches": 0
    },
    "image_name": "20241221_100711_257_IR_inferno",
    "pair_name": "pair_0009"
  },
  {
    "success": false,
    "error": "No keypoints detected",
    "num_keypoints_A": 3,
    "num_keypoints_B": 0,
    "image_name": "20241221_100711_257_IR_inferno",
    "pair_name": "pair_0010"
  },
  {
    "success": false,
    "error": "No keypoints detected",
    "num_keypoints_A": 0,
    "num_keypoints_B": 0,
    "image_name": "20241222_081954_680_IR_inferno",
    "pair_name": "pair_0001"
  },
  {
    "success": false,
    "error": "No keypoints detected",
    "num_keypoints_A": 0,
    "num_keypoints_B": 0,
    "image_name": "20241222_081954_680_IR_inferno",
    "pair_name": "pair_0002"
  },
  {
    "success": false,
    "error": "No keypoints detected",
    "num_keypoints_A": 0,
    "num_keypoints_B": 0,
    "image_name": "20241222_081954_680_IR_inferno",
    "pair_name": "pair_0003"
  },
  {
    "success": false,
    "error": "No keypoints detected",
    "num_keypoints_A": 0,
    "num_keypoints_B": 0,
    "image_name": "20241222_081954_680_IR_inferno",
    "pair_name": "pair_0004"
  },
  {
    "success": false,
    "error": "No keypoints detected",
    "num_keypoints_A": 0,
    "num_keypoints_B": 0,
    "image_name": "20241222_081954_680_IR_inferno",
    "pair_name": "pair_0005"
  },
  {
    "success": false,
    "error": "No keypoints detected",
    "num_keypoints_A": 0,
    "num_keypoints_B": 0,
    "image_name": "20241222_081954_680_IR_inferno",
    "pair_name": "pair_0006"
  },
  {
    "success": false,
    "error": "No keypoints detected",
    "num_keypoints_A": 0,
    "num_keypoints_B": 0,
    "image_name": "20241222_081954_680_IR_inferno",
    "pair_name": "pair_0007"
  },
  {
    "success": false,
    "error": "No keypoints detected",
    "num_keypoints_A": 0,
    "num_keypoints_B": 0,
    "image_name": "20241222_081954_680_IR_inferno",
    "pair_name": "pair_0008"
  },
  {
    "success": false,
    "error": "No keypoints detected",
    "num_keypoints_A": 0,
    "num_keypoints_B": 0,
    "image_name": "20241222_081954_680_IR_inferno",
    "pair_name": "pair_0009"
  },
  {
    "success": false,
    "error": "No keypoints detected",
    "num_keypoints_A": 0,
    "num_keypoints_B": 0,
    "image_name": "20241222_141317_881_IR_inferno",
    "pair_name": "pair_0001"
  },
  {
    "success": false,
    "error": "No keypoints detected",
    "num_keypoints_A": 0,
    "num_keypoints_B": 0,
    "image_name": "20241222_141317_881_IR_inferno",
    "pair_name": "pair_0002"
  },
  {
    "success": false,
    "error": "No keypoints detected",
    "num_keypoints_A": 1,
    "num_keypoints_B": 0,
    "image_name": "20241222_141317_881_IR_inferno",
    "pair_name": "pair_0003"
  },
  {
    "success": false,
    "error": "No keypoints detected",
    "num_keypoints_A": 0,
    "num_keypoints_B": 0,
    "image_name": "20241222_141317_881_IR_inferno",
    "pair_name": "pair_0004"
  },
  {
    "success": false,
    "error": "No keypoints detected",
    "num_keypoints_A": 3,
    "num_keypoints_B": 0,
    "image_name": "20241222_141317_881_IR_inferno",
    "pair_name": "pair_0005"
  },
  {
    "success": false,
    "error": "No keypoints detected",
    "num_keypoints_A": 0,
    "num_keypoints_B": 0,
    "image_name": "20241222_141317_881_IR_inferno",
    "pair_name": "pair_0006"
  },
  {
    "success": false,
    "error": "No keypoints detected",
    "num_keypoints_A": 0,
    "num_keypoints_B": 0,
    "image_name": "20241222_141317_881_IR_inferno",
    "pair_name": "pair_0007"
  },
  {
    "success": false,
    "error": "No keypoints detected",
    "num_keypoints_A": 0,
    "num_keypoints_B": 0,
    "image_name": "20241222_141317_881_IR_inferno",
    "pair_name": "pair_0008"
  },
  {
    "success": false,
    "error": "No keypoints detected",
    "num_keypoints_A": 0,
    "num_keypoints_B": 0,
    "image_name": "20241222_141317_881_IR_inferno",
    "pair_name": "pair_0009"
  },
  {
    "success": false,
    "error": "No keypoints detected",
    "num_keypoints_A": 0,
    "num_keypoints_B": 0,
    "image_name": "20241222_141317_881_IR_inferno",
    "pair_name": "pair_0010"
  },
  {
    "success": false,
    "error": "No keypoints detected",
    "num_keypoints_A": 0,
    "num_keypoints_B": 0,
    "image_name": "20241223_120131_487_IR_inferno",
    "pair_name": "pair_0001"
  },
  {
    "success": false,
    "error": "No keypoints detected",
    "num_keypoints_A": 0,
    "num_keypoints_B": 0,
    "image_name": "20241223_120131_487_IR_inferno",
    "pair_name": "pair_0002"
  },
  {
    "success": false,
    "error": "No keypoints detected",
    "num_keypoints_A": 0,
    "num_keypoints_B": 0,
    "image_name": "20241223_120131_487_IR_inferno",
    "pair_name": "pair_0003"
  },
  {
    "success": false,
    "error": "No keypoints detected",
    "num_keypoints_A": 0,
    "num_keypoints_B": 0,
    "image_name": "20241223_120131_487_IR_inferno",
    "pair_name": "pair_0004"
  },
  {
    "success": false,
    "error": "No keypoints detected",
    "num_keypoints_A": 0,
    "num_keypoints_B": 0,
    "image_name": "20241223_120131_487_IR_inferno",
    "pair_name": "pair_0005"
  },
  {
    "success": false,
    "error": "No keypoints detected",
    "num_keypoints_A": 0,
    "num_keypoints_B": 0,
    "image_name": "20241223_120131_487_IR_inferno",
    "pair_name": "pair_0006"
  },
  {
    "success": false,
    "error": "No keypoints detected",
    "num_keypoints_A": 0,
    "num_keypoints_B": 0,
    "image_name": "20241223_120131_487_IR_inferno",
    "pair_name": "pair_0007"
  },
  {
    "success": false,
    "error": "No keypoints detected",
    "num_keypoints_A": 0,
    "num_keypoints_B": 0,
    "image_name": "20241223_120131_487_IR_inferno",
    "pair_name": "pair_0008"
  },
  {
    "success": false,
    "error": "No keypoints detected",
    "num_keypoints_A": 0,
    "num_keypoints_B": 0,
    "image_name": "20241223_120131_487_IR_inferno",
    "pair_name": "pair_0009"
  },
  {
    "success": false,
    "error": "No keypoints detected",
    "num_keypoints_A": 0,
    "num_keypoints_B": 0,
    "image_name": "20241223_120131_487_IR_inferno",
    "pair_name": "pair_0010"
  },
  {
    "success": false,
    "error": "No keypoints detected",
    "num_keypoints_A": 0,
    "num_keypoints_B": 0,
    "image_name": "20241223_120707_069_IR_inferno",
    "pair_name": "pair_0001"
  },
  {
    "success": false,
    "error": "No keypoints detected",
    "num_keypoints_A": 0,
    "num_keypoints_B": 0,
    "image_name": "20241223_120707_069_IR_inferno",
    "pair_name": "pair_0002"
  },
  {
    "success": false,
    "error": "No keypoints detected",
    "num_keypoints_A": 0,
    "num_keypoints_B": 0,
    "image_name": "20241223_120707_069_IR_inferno",
    "pair_name": "pair_0003"
  },
  {
    "success": false,
    "error": "No keypoints detected",
    "num_keypoints_A": 1,
    "num_keypoints_B": 0,
    "image_name": "20241223_120707_069_IR_inferno",
    "pair_name": "pair_0004"
  },
  {
    "success": false,
    "error": "No keypoints detected",
    "num_keypoints_A": 0,
    "num_keypoints_B": 0,
    "image_name": "20241223_120707_069_IR_inferno",
    "pair_name": "pair_0005"
  },
  {
    "success": false,
    "error": "No keypoints detected",
    "num_keypoints_A": 3,
    "num_keypoints_B": 0,
    "image_name": "20241223_120707_069_IR_inferno",
    "pair_name": "pair_0006"
  },
  {
    "success": false,
    "error": "No keypoints detected",
    "num_keypoints_A": 2,
    "num_keypoints_B": 0,
    "image_name": "20241223_120707_069_IR_inferno",
    "pair_name": "pair_0007"
  },
  {
    "success": false,
    "error": "Insufficient matches",
    "num_keypoints_A": 2,
    "num_keypoints_B": 1,
    "num_matches": 0,
    "matching_stats": {
      "error": "Insufficient descriptors",
      "good_matches": 0
    },
    "image_name": "20241223_120707_069_IR_inferno",
    "pair_name": "pair_0008"
  },
  {
    "success": false,
    "error": "No keypoints detected",
    "num_keypoints_A": 2,
    "num_keypoints_B": 0,
    "image_name": "20241223_120707_069_IR_inferno",
    "pair_name": "pair_0009"
  },
  {
    "success": false,
    "error": "No keypoints detected",
    "num_keypoints_A": 2,
    "num_keypoints_B": 0,
    "image_name": "20241223_120707_069_IR_inferno",
    "pair_name": "pair_0010"
  }
]